urlsearch/__init__.py
urlsearch/default_config.py
urlsearch/urlsearch.py
urlsearch-0.3.3.data/scripts/bing
urlsearch-0.3.3.data/scripts/ddg
urlsearch-0.3.3.data/scripts/google
urlsearch-0.3.3.data/scripts/pylib
urlsearch-0.3.3.data/scripts/pypi
urlsearch-0.3.3.data/scripts/urlsearch
urlsearch-0.3.3.data/scripts/wiki
urlsearch-0.3.3.dist-info/DESCRIPTION.rst
urlsearch-0.3.3.dist-info/METADATA
urlsearch-0.3.3.dist-info/metadata.json
urlsearch-0.3.3.dist-info/RECORD
urlsearch-0.3.3.dist-info/top_level.txt
urlsearch-0.3.3.dist-info/WHEEL
