Metadata-Version: 2.0
Name: urlsearch
Version: 0.3.3
Summary: perform web searches from the command line
Home-page: http://bitbucket.org/codedstructure/urlsearch
Author: Ben Bass
Author-email: benbass@codedstructure.net
License: UNKNOWN
Platform: UNKNOWN
Classifier: Development Status :: 4 - Beta
Classifier: Environment :: Console
Classifier: License :: OSI Approved :: MIT License
Classifier: Operating System :: POSIX
Classifier: Programming Language :: Python
Classifier: Programming Language :: Python :: 2.7
Classifier: Programming Language :: Python :: 3
Classifier: Programming Language :: Python :: 3.2
Classifier: Programming Language :: Python :: 3.3
Classifier: Programming Language :: Python :: 3.4
